cucaracha/__init__.py
cucaracha/configuration.py
cucaracha/ml_models/__init__.py
cucaracha/ml_models/image_classification/__init__.py
cucaracha/ml_models/image_classification/alex_net.py
cucaracha/ml_models/image_classification/dense_net_121.py
cucaracha/ml_models/image_classification/google_le_net.py
cucaracha/ml_models/image_classification/model_soup.py
cucaracha/ml_models/image_classification/res_net_50.py
cucaracha/ml_models/image_classification/small_xception.py
cucaracha/ml_models/image_segmentation/__init__.py
cucaracha/ml_models/image_segmentation/unet_xception.py
cucaracha/ml_models/kaggle_helpers.py
cucaracha/ml_models/model_architect.py
cucaracha/ml_trainers/__init__.py
cucaracha/ml_trainers/image_classification_trainer.py
cucaracha/ml_trainers/image_segmentation_trainer.py
cucaracha/ml_trainers/keypoint_detection_modeling.py
cucaracha/ml_trainers/keypoint_generator.py
cucaracha/ml_trainers/ml_pattern.py
cucaracha/scripts/image_classification_builder.py
cucaracha/scripts/image_classification_evaluate_model.py
cucaracha/scripts/image_dataset_augmentation.py
cucaracha/tasks/__init__.py
cucaracha/tasks/aligment.py
cucaracha/tasks/identification.py
cucaracha/tasks/noise_removal.py
cucaracha/tasks/threshold.py
cucaracha/utils.py
cucaracha-0.6.0.dist-info/LICENSE
cucaracha-0.6.0.dist-info/METADATA
cucaracha-0.6.0.dist-info/WHEEL
cucaracha-0.6.0.dist-info/RECORD
