Metadata-Version: 2.1
Name: cucaracha
Version: 0.6.0
Summary: Mr. Franz Cucaracha will be glad to assist you to the document analysis and processing routine
License: MIT
Author: Antonio Senra Filho
Author-email: acsenrafilho@gmail.com
Requires-Python: >=3.10,<3.13
Classifier: License :: OSI Approved :: MIT License
Classifier: Operating System :: OS Independent
Classifier: Programming Language :: Python :: 3
Classifier: Programming Language :: Python :: 3.10
Classifier: Programming Language :: Python :: 3.11
Classifier: Programming Language :: Python :: 3.12
Classifier: Topic :: Scientific/Engineering
Classifier: Topic :: Scientific/Engineering :: Artificial Intelligence
Classifier: Topic :: Scientific/Engineering :: Image Processing
Classifier: Topic :: Scientific/Engineering :: Image Recognition
Classifier: Topic :: Scientific/Engineering :: Information Analysis
Requires-Dist: kagglehub (>=0.3.4,<0.4.0)
Requires-Dist: numpy (>=1.22.4,<2.0.0)
Requires-Dist: opencv-python (>=4.10.0.84,<5.0.0.0)
Requires-Dist: pymupdf (>=1.24.13,<2.0.0)
Requires-Dist: rich (>=13.9.3,<14.0.0)
Requires-Dist: scikit-learn (>=1.6.1,<2.0.0)
Requires-Dist: scipy (>=1.15.1,<2.0.0)
Requires-Dist: seaborn (>=0.13.2,<0.14.0)
Requires-Dist: tensorflow (==2.16.2)
Requires-Dist: tensorflow-io-gcs-filesystem (==0.37.1)
Project-URL: Code, https://github.com/acsenrafilho/cucaracha
Project-URL: Code Issues, https://github.com/acsenrafilho/cucaracha/issues
Project-URL: Documentation, https://cucaracha.readthedocs.io/en/latest/
